py_iex/__init__.py
py_iex/iex.py
py_iex/market_data.py
py_iex/markets.py
py_iex/reference_data.py
py_iex/stats.py
py_iex/stocks.py
py_iex-0.0.3.dist-info/DESCRIPTION.rst
py_iex-0.0.3.dist-info/METADATA
py_iex-0.0.3.dist-info/RECORD
py_iex-0.0.3.dist-info/WHEEL
py_iex-0.0.3.dist-info/metadata.json
py_iex-0.0.3.dist-info/top_level.txt
