Metadata-Version: 2.0
Name: py-iex
Version: 0.0.3
Summary: Python module to get stock data from IEX API
Home-page: https://github.com/jxzym25/py_iex
Author: Jerry Chou
Author-email: jxzym25@gmail.com
License: MIT
Keywords: iex,py_iex,stock,price,finance,quotes
Platform: UNKNOWN
Classifier: Development Status :: 3 - Alpha
Classifier: Intended Audience :: Developers
Classifier: Topic :: Office/Business :: Financial :: Investment
Classifier: License :: OSI Approved :: MIT License
Classifier: Programming Language :: Python :: 2.7
Classifier: Programming Language :: Python :: 3.4
Classifier: Programming Language :: Python :: 3.5
Classifier: Programming Language :: Python :: 3.6
Requires-Dist: requests
